02_basic_RTL/04_sequential_logics/latch_vs_dff/latch_vs_dff.v
// ==================================================
//	[ VLSISYS Lab. ]
//	* Author		: SoJeong Ok (oksj@sookmyung.ac.kr)
//	* Filename		: latch_vs_dff.v
//	* Date			: 2024-09-13 15:57:26
//	* Description	: 
// ==================================================

module latch	
(
	output	reg		o_q,
	input			i_d,
	input			i_clk
);

	always @(*) begin
		if(i_clk) begin
			o_q		<= i_d;
		end
	end
	
endmodule


module dff 
(
	output	reg		o_q,
	input			i_d,
	input			i_clk
);

	always @(posedge i_clk) begin
		o_q		<= i_d;
	end
	
endmodule

02_basic_RTL/04_sequential_logics/latch_vs_dff/latch_vs_dff_tb.v
// ==================================================
//	[ VLSISYS Lab. ]
//	* Author		: SoJeong Ok (oksj@sookmyung.ac.kr)
//	* Filename		: latch_vs_dff_tb.v
//	* Date			: 2024-09-13 19:18:23
//	* Description	: 
// ==================================================

// --------------------------------------------------
//	Define Global Variables
// --------------------------------------------------
`define	CLKFREQ		100		// Clock Freq. (Unit: MHz)
`define	SIMCYCLE	50		// Sim. Cycles

// --------------------------------------------------
//	Includes
// --------------------------------------------------
`include	"latch_vs_dff.v"

module latch_vs_dff_tb;
// --------------------------------------------------
//	DUT Signals & Instantiate
// --------------------------------------------------
	wire			o_q_lat;
	wire			o_q_dff;
	reg				i_d;
	reg				i_clk;

	latch
	u_latch(
		.o_q				(o_q_lat 			),
		.i_d				(i_d				),
		.i_clk				(i_clk				)
	);


	dff
	u_dff(
		.o_q				(o_q_dff			),
		.i_d				(i_d				),
		.i_clk				(i_clk				)
	);


// --------------------------------------------------
//	Clock
// --------------------------------------------------
	always #(500/`CLKFREQ) i_clk = ~i_clk;
// --------------------------------------------------
//	Tasks
// --------------------------------------------------
	task init;
		begin
			i_d		= 0;
			i_clk	= 0;
		end
	endtask
// --------------------------------------------------
//	Test Stimulus
// --------------------------------------------------
	integer		i, j;
	initial begin
		init();
		for (i=0; i<`SIMCYCLE; i++) begin
			j	= $urandom_range(0,10);
			#((   (j*0.1)) * 1000/`CLKFREQ);
			i_d = $urandom;
			#((1- (j*0.1)) * 1000/`CLKFREQ);
		end
		$finish;
	end

// --------------------------------------------------
//	Dump VCD
// --------------------------------------------------
	reg	[8*32-1:0]	vcd_file;
	initial begin
		if ($value$plusargs("vcd_file=%s", vcd_file)) begin
			$dumpfile(vcd_file);
			$dumpvars;
		end else begin
			$dumpfile("latch_vs_dff_tb.vcd");
			$dumpvars;
		end
	end

endmodule

02_basic_RTL/04_sequential_logics/latch_vs_dff/vcd/latch_vs_dff.vcd
$date
	Fri Sep 13 19:27:12 2024
$end
$version
	Icarus Verilog
$end
$timescale
	1ps
$end
$scope module latch_vs_dff_tb $end
$var wire 1 ! o_q_lat $end
$var wire 1 " o_q_dff $end
$var reg 1 # i_clk $end
$var reg 1 $ i_d $end
$var reg 256 % vcd_file [255:0] $end
$var integer 32 & i [31:0] $end
$var integer 32 ' j [31:0] $end
$scope module u_dff $end
$var wire 1 # i_clk $end
$var wire 1 $ i_d $end
$var reg 1 " o_q $end
$upscope $end
$scope module u_latch $end
$var wire 1 # i_clk $end
$var wire 1 $ i_d $end
$var reg 1 ! o_q $end
$upscope $end
$scope task init $end
$upscope $end
$upscope $end
$enddefinitions $end
#0
$dumpvars
b110 '
b0 &
b101110001011110111011001100011011001000010111101101100011000010111010001100011011010000101111101110110011100110101111101100100011001100110011000101110011101100110001101100100 %
0$
0#
x"
x!
$end
#5000
0"
0!
1#
#6000
1!
1$
#10000
b0 '
b1 &
0#
#15000
1"
1#
#20000
0#
b101 '
b10 &
#25000
1#
#30000
0#
b10 '
b11 &
#32000
0$
#35000
0"
0!
1#
#40000
0#
b101 '
b100 &
#45000
1"
1!
1#
1$
#50000
0#
b1000 '
b101 &
#55000
1#
#60000
b1010 '
b110 &
0#
#65000
1#
#70000
b111 &
0#
0$
#75000
0"
0!
1#
#80000
b100 '
b1000 &
0#
#85000
1#
#90000
0#
b1010 '
b1001 &
#95000
1#
#100000
b0 '
b1010 &
0#
1$
#105000
1"
1!
1#
#110000
0#
b1010 '
b1011 &
#115000
1#
#120000
b100 '
b1100 &
0#
0$
#124000
1$
#125000
1#
#130000
0#
b111 '
b1101 &
#135000
1#
#140000
b0 '
b1110 &
0#
#145000
1#
#150000
0#
b10 '
b1111 &
#152000
0$
#155000
0"
0!
1#
#160000
0#
b10000 &
#165000
1#
#170000
0#
b1001 '
b10001 &
#175000
1#
#179000
1!
1$
#180000
b11 '
b10010 &
0#
#185000
1"
1#
#190000
0#
b0 '
b10011 &
#195000
1#
#200000
0#
b111 '
b10100 &
#205000
1#
#210000
0$
b0 '
b10101 &
0#
#215000
0"
0!
1#
#220000
0#
b110 '
b10110 &
#225000
1#
#226000
1!
1$
#230000
b10111 &
0#
#235000
1"
1#
#236000
0!
0$
#240000
b100 '
b11000 &
0#
#245000
0"
1#
#250000
0#
b1010 '
b11001 &
#255000
1#
#260000
b110 '
b11010 &
0#
#265000
1#
#270000
b1000 '
b11011 &
0#
#275000
1#
#278000
1!
1$
#280000
b1010 '
b11100 &
0#
#285000
1"
1#
#290000
b1001 '
b11101 &
0#
0$
#295000
0"
0!
1#
#300000
b100 '
b11110 &
0#
#305000
1#
#310000
1$
0#
b0 '
b11111 &
#315000
1"
1!
1#
#320000
0#
b1000 '
b100000 &
#325000
1#
#330000
b1 '
b100001 &
0#
#331000
0$
#335000
0"
0!
1#
#340000
0#
b10 '
b100010 &
#342000
1$
#345000
1"
1!
1#
#350000
0#
b1010 '
b100011 &
#355000
1#
#360000
b111 '
b100100 &
0#
#365000
1#
#367000
0!
0$
#370000
b1000 '
b100101 &
0#
#375000
0"
1#
#378000
1!
1$
#380000
b1010 '
b100110 &
0#
#385000
1"
1#
#390000
b11 '
b100111 &
0#
#393000
0$
#395000
0"
0!
1#
#400000
0#
b1 '
b101000 &
#401000
1$
#405000
1"
1!
1#
#410000
0#
b101001 &
#411000
0$
#415000
0"
0!
1#
#420000
0#
b100 '
b101010 &
#424000
1$
#425000
1"
1!
1#
#430000
0#
b1000 '
b101011 &
#435000
1#
#438000
0!
0$
#440000
b100 '
b101100 &
0#
#445000
0"
1#
#450000
0#
b10 '
b101101 &
#452000
1$
#455000
1"
1!
1#
#460000
0#
b101 '
b101110 &
#465000
0"
0!
1#
0$
#470000
0#
b111 '
b101111 &
#475000
1#
#477000
1!
1$
#480000
b110 '
b110000 &
0#
#485000
1"
1#
#490000
b1000 '
b110001 &
0#
#495000
1#
#498000
0!
0$
#500000
b110010 &
0#
