03_project_advanced_RTL/00_gray_code_converter/gray_code_converter.v
// ==================================================
//	[ VLSISYS Lab. ]
//	* Author		: SoJeong Ok (oksj@sookmyung.ac.kr)
//	* Filename		: gray_code_converter.v
//	* Date			: 2024-09-23 17:36:26
//	* Description	: 
// ==================================================

// Convert Binary to Graycode
module bin_to_gray
#(	
	parameter	BW_DATA			= 8 
)
(	
	output 		[BW_DATA-1:0]	out_gray,
	input		[BW_DATA-1:0]	in_bin
);

	assign		out_gray[BW_DATA-1]	= in_bin[BW_DATA-1];		// MSB is always same

	genvar		i;
	generate
		for	(i=0; i<BW_DATA-1; i=i+1) begin
			assign	out_gray[i]	= in_bin[i+1] ^ in_bin[i];	// xor
		end
	endgenerate

endmodule


// Convert Gray to Binary
module gray_to_bin 
#(	
	parameter	BW_DATA			= 8
)
(
	output		[BW_DATA-1:0]	out_bin,
	input		[BW_DATA-1:0]	in_gray
);

	assign		out_bin[BW_DATA-1]	= in_gray[BW_DATA-1];

	genvar		i;
	generate
		for	(i=BW_DATA-2; i>=0; i=i-1) begin
			assign	out_bin[i]	= out_bin[i+1] ^ in_gray[i];
		end
	endgenerate

endmodule

03_project_advanced_RTL/00_gray_code_converter/gray_code_converter_tb.v
// ==================================================
//	[ VLSISYS Lab. ]
//	* Author		: SoJeong Ok (oksj@sookmyung.ac.kr)
//	* Filename		: gray_code_converter_tb.v
//	* Date			: 2024-09-23 17:59:11
//	* Description	: 
// ==================================================

// --------------------------------------------------
//	Define Global Variables
// --------------------------------------------------
`define	CLKFREQ		100		// Clock Freq. (Unit: MHz)
`define	SIMCYCLE	`NVEC	// Sim. Cycles
`define NVEC		100		// # of Test Vector

// --------------------------------------------------
//	Includes
// --------------------------------------------------
`include	"gray_code_converter.v"

module gray_code_converter_tb;
// --------------------------------------------------
//	DUT Signals & Instantiate
// --------------------------------------------------
	parameter		BW_DATA		= 8;

	wire			[BW_DATA-1:0]	out_gray;
	wire			[BW_DATA-1:0]	out_bin;
	reg				[BW_DATA-1:0]	i_data;

	// First, input i_data to "bin_to_gray" module. 
	// Next, out_gray go in "gray_to_bin" module.
	// Binary(i_data) -> Gray(out_gray) -> Binary(out_bin)
	
	bin_to_gray
	#(
		.BW_DATA			(BW_DATA			)
	)
	u_bin_to_gray(
		.out_gray			(out_gray			),
		.in_bin				(i_data				)
	);

	gray_to_bin	
	#(
		.BW_DATA			(BW_DATA			)
	)
	u_gray_to_bin(
		.out_bin			(out_bin			),
		.in_gray			(out_gray			)
	);

// --------------------------------------------------
//	Tasks
// --------------------------------------------------
	task	init;
		begin
			i_data	= 0;
		end
	endtask
// --------------------------------------------------
//	Test Stimulus
// --------------------------------------------------
	integer		i, j;
	initial begin
		init();
		for (i=0; i<`SIMCYCLE; i++) begin
			i_data	= i;
			#(1000/`CLKFREQ);
		end
		$finish;
	end

// --------------------------------------------------
//	Dump VCD
// --------------------------------------------------
	reg	[8*32-1:0]	vcd_file;
	initial begin
		if ($value$plusargs("vcd_file=%s", vcd_file)) begin
			$dumpfile(vcd_file);
			$dumpvars;
		end else begin
			$dumpfile("gray_code_converter_tb.vcd");
			$dumpvars;
		end
	end

endmodule

03_project_advanced_RTL/00_gray_code_converter/vcd/gray_code_converter.vcd
$date
	Mon Sep 23 18:10:43 2024
$end
$version
	Icarus Verilog
$end
$timescale
	1ps
$end
$scope module gray_code_converter_tb $end
$var wire 8 ! out_gray [7:0] $end
$var wire 8 " out_bin [7:0] $end
$var reg 8 # i_data [7:0] $end
$var reg 256 $ vcd_file [255:0] $end
$var integer 32 % i [31:0] $end
$scope module u_bin_to_gray $end
$var wire 8 & in_bin [7:0] $end
$var wire 8 ' out_gray [7:0] $end
$scope begin genblk1[0] $end
$upscope $end
$scope begin genblk1[1] $end
$upscope $end
$scope begin genblk1[2] $end
$upscope $end
$scope begin genblk1[3] $end
$upscope $end
$scope begin genblk1[4] $end
$upscope $end
$scope begin genblk1[5] $end
$upscope $end
$scope begin genblk1[6] $end
$upscope $end
$upscope $end
$scope module u_gray_to_bin $end
$var wire 8 ( in_gray [7:0] $end
$var wire 8 ) out_bin [7:0] $end
$scope begin genblk1[0] $end
$upscope $end
$scope begin genblk1[1] $end
$upscope $end
$scope begin genblk1[2] $end
$upscope $end
$scope begin genblk1[3] $end
$upscope $end
$scope begin genblk1[4] $end
$upscope $end
$scope begin genblk1[5] $end
$upscope $end
$scope begin genblk1[6] $end
$upscope $end
$upscope $end
$scope task init $end
$upscope $end
$upscope $end
$enddefinitions $end
#0
$dumpvars
b0 )
b0 (
b0 '
b0 &
b0 %
b10111000101111011101100110001101100100001011110110011101110010011000010111100101011111011000110110111101100100011001010101111101100011011011110110111001110110011001010111001001110100011001010111001000101110011101100110001101100100 $
b0 #
b0 "
b0 !
$end
#10000
b1 "
b1 )
b1 !
b1 '
b1 (
b1 #
b1 &
b1 %
#20000
b10 "
b10 )
b11 !
b11 '
b11 (
b10 #
b10 &
b10 %
#30000
b11 "
b11 )
b10 !
b10 '
b10 (
b11 #
b11 &
b11 %
#40000
b100 "
b100 )
b110 !
b110 '
b110 (
b100 #
b100 &
b100 %
#50000
b101 "
b101 )
b111 !
b111 '
b111 (
b101 #
b101 &
b101 %
#60000
b110 "
b110 )
b101 !
b101 '
b101 (
b110 #
b110 &
b110 %
#70000
b111 "
b111 )
b100 !
b100 '
b100 (
b111 #
b111 &
b111 %
#80000
b1000 "
b1000 )
b1100 !
b1100 '
b1100 (
b1000 #
b1000 &
b1000 %
#90000
b1001 "
b1001 )
b1101 !
b1101 '
b1101 (
b1001 #
b1001 &
b1001 %
#100000
b1010 "
b1010 )
b1111 !
b1111 '
b1111 (
b1010 #
b1010 &
b1010 %
#110000
b1011 "
b1011 )
b1110 !
b1110 '
b1110 (
b1011 #
b1011 &
b1011 %
#120000
b1100 "
b1100 )
b1010 !
b1010 '
b1010 (
b1100 #
b1100 &
b1100 %
#130000
b1101 "
b1101 )
b1011 !
b1011 '
b1011 (
b1101 #
b1101 &
b1101 %
#140000
b1110 "
b1110 )
b1001 !
b1001 '
b1001 (
b1110 #
b1110 &
b1110 %
#150000
b1111 "
b1111 )
b1000 !
b1000 '
b1000 (
b1111 #
b1111 &
b1111 %
#160000
b10000 "
b10000 )
b11000 !
b11000 '
b11000 (
b10000 #
b10000 &
b10000 %
#170000
b10001 "
b10001 )
b11001 !
b11001 '
b11001 (
b10001 #
b10001 &
b10001 %
#180000
b10010 "
b10010 )
b11011 !
b11011 '
b11011 (
b10010 #
b10010 &
b10010 %
#190000
b10011 "
b10011 )
b11010 !
b11010 '
b11010 (
b10011 #
b10011 &
b10011 %
#200000
b10100 "
b10100 )
b11110 !
b11110 '
b11110 (
b10100 #
b10100 &
b10100 %
#210000
b10101 "
b10101 )
b11111 !
b11111 '
b11111 (
b10101 #
b10101 &
b10101 %
#220000
b10110 "
b10110 )
b11101 !
b11101 '
b11101 (
b10110 #
b10110 &
b10110 %
#230000
b10111 "
b10111 )
b11100 !
b11100 '
b11100 (
b10111 #
b10111 &
b10111 %
#240000
b11000 "
b11000 )
b10100 !
b10100 '
b10100 (
b11000 #
b11000 &
b11000 %
#250000
b11001 "
b11001 )
b10101 !
b10101 '
b10101 (
b11001 #
b11001 &
b11001 %
#260000
b11010 "
b11010 )
b10111 !
b10111 '
b10111 (
b11010 #
b11010 &
b11010 %
#270000
b11011 "
b11011 )
b10110 !
b10110 '
b10110 (
b11011 #
b11011 &
b11011 %
#280000
b11100 "
b11100 )
b10010 !
b10010 '
b10010 (
b11100 #
b11100 &
b11100 %
#290000
b11101 "
b11101 )
b10011 !
b10011 '
b10011 (
b11101 #
b11101 &
b11101 %
#300000
b11110 "
b11110 )
b10001 !
b10001 '
b10001 (
b11110 #
b11110 &
b11110 %
#310000
b11111 "
b11111 )
b10000 !
b10000 '
b10000 (
b11111 #
b11111 &
b11111 %
#320000
b100000 "
b100000 )
b110000 !
b110000 '
b110000 (
b100000 #
b100000 &
b100000 %
#330000
b100001 "
b100001 )
b110001 !
b110001 '
b110001 (
b100001 #
b100001 &
b100001 %
#340000
b100010 "
b100010 )
b110011 !
b110011 '
b110011 (
b100010 #
b100010 &
b100010 %
#350000
b100011 "
b100011 )
b110010 !
b110010 '
b110010 (
b100011 #
b100011 &
b100011 %
#360000
b100100 "
b100100 )
b110110 !
b110110 '
b110110 (
b100100 #
b100100 &
b100100 %
#370000
b100101 "
b100101 )
b110111 !
b110111 '
b110111 (
b100101 #
b100101 &
b100101 %
#380000
b100110 "
b100110 )
b110101 !
b110101 '
b110101 (
b100110 #
b100110 &
b100110 %
#390000
b100111 "
b100111 )
b110100 !
b110100 '
b110100 (
b100111 #
b100111 &
b100111 %
#400000
b101000 "
b101000 )
b111100 !
b111100 '
b111100 (
b101000 #
b101000 &
b101000 %
#410000
b101001 "
b101001 )
b111101 !
b111101 '
b111101 (
b101001 #
b101001 &
b101001 %
#420000
b101010 "
b101010 )
b111111 !
b111111 '
b111111 (
b101010 #
b101010 &
b101010 %
#430000
b101011 "
b101011 )
b111110 !
b111110 '
b111110 (
b101011 #
b101011 &
b101011 %
#440000
b101100 "
b101100 )
b111010 !
b111010 '
b111010 (
b101100 #
b101100 &
b101100 %
#450000
b101101 "
b101101 )
b111011 !
b111011 '
b111011 (
b101101 #
b101101 &
b101101 %
#460000
b101110 "
b101110 )
b111001 !
b111001 '
b111001 (
b101110 #
b101110 &
b101110 %
#470000
b101111 "
b101111 )
b111000 !
b111000 '
b111000 (
b101111 #
b101111 &
b101111 %
#480000
b110000 "
b110000 )
b101000 !
b101000 '
b101000 (
b110000 #
b110000 &
b110000 %
#490000
b110001 "
b110001 )
b101001 !
b101001 '
b101001 (
b110001 #
b110001 &
b110001 %
#500000
b110010 "
b110010 )
b101011 !
b101011 '
b101011 (
b110010 #
b110010 &
b110010 %
#510000
b110011 "
b110011 )
b101010 !
b101010 '
b101010 (
b110011 #
b110011 &
b110011 %
#520000
b110100 "
b110100 )
b101110 !
b101110 '
b101110 (
b110100 #
b110100 &
b110100 %
#530000
b110101 "
b110101 )
b101111 !
b101111 '
b101111 (
b110101 #
b110101 &
b110101 %
#540000
b110110 "
b110110 )
b101101 !
b101101 '
b101101 (
b110110 #
b110110 &
b110110 %
#550000
b110111 "
b110111 )
b101100 !
b101100 '
b101100 (
b110111 #
b110111 &
b110111 %
#560000
b111000 "
b111000 )
b100100 !
b100100 '
b100100 (
b111000 #
b111000 &
b111000 %
#570000
b111001 "
b111001 )
b100101 !
b100101 '
b100101 (
b111001 #
b111001 &
b111001 %
#580000
b111010 "
b111010 )
b100111 !
b100111 '
b100111 (
b111010 #
b111010 &
b111010 %
#590000
b111011 "
b111011 )
b100110 !
b100110 '
b100110 (
b111011 #
b111011 &
b111011 %
#600000
b111100 "
b111100 )
b100010 !
b100010 '
b100010 (
b111100 #
b111100 &
b111100 %
#610000
b111101 "
b111101 )
b100011 !
b100011 '
b100011 (
b111101 #
b111101 &
b111101 %
#620000
b111110 "
b111110 )
b100001 !
b100001 '
b100001 (
b111110 #
b111110 &
b111110 %
#630000
b111111 "
b111111 )
b100000 !
b100000 '
b100000 (
b111111 #
b111111 &
b111111 %
#640000
b1000000 "
b1000000 )
b1100000 !
b1100000 '
b1100000 (
b1000000 #
b1000000 &
b1000000 %
#650000
b1000001 "
b1000001 )
b1100001 !
b1100001 '
b1100001 (
b1000001 #
b1000001 &
b1000001 %
#660000
b1000010 "
b1000010 )
b1100011 !
b1100011 '
b1100011 (
b1000010 #
b1000010 &
b1000010 %
#670000
b1000011 "
b1000011 )
b1100010 !
b1100010 '
b1100010 (
b1000011 #
b1000011 &
b1000011 %
#680000
b1000100 "
b1000100 )
b1100110 !
b1100110 '
b1100110 (
b1000100 #
b1000100 &
b1000100 %
#690000
b1000101 "
b1000101 )
b1100111 !
b1100111 '
b1100111 (
b1000101 #
b1000101 &
b1000101 %
#700000
b1000110 "
b1000110 )
b1100101 !
b1100101 '
b1100101 (
b1000110 #
b1000110 &
b1000110 %
#710000
b1000111 "
b1000111 )
b1100100 !
b1100100 '
b1100100 (
b1000111 #
b1000111 &
b1000111 %
#720000
b1001000 "
b1001000 )
b1101100 !
b1101100 '
b1101100 (
b1001000 #
b1001000 &
b1001000 %
#730000
b1001001 "
b1001001 )
b1101101 !
b1101101 '
b1101101 (
b1001001 #
b1001001 &
b1001001 %
#740000
b1001010 "
b1001010 )
b1101111 !
b1101111 '
b1101111 (
b1001010 #
b1001010 &
b1001010 %
#750000
b1001011 "
b1001011 )
b1101110 !
b1101110 '
b1101110 (
b1001011 #
b1001011 &
b1001011 %
#760000
b1001100 "
b1001100 )
b1101010 !
b1101010 '
b1101010 (
b1001100 #
b1001100 &
b1001100 %
#770000
b1001101 "
b1001101 )
b1101011 !
b1101011 '
b1101011 (
b1001101 #
b1001101 &
b1001101 %
#780000
b1001110 "
b1001110 )
b1101001 !
b1101001 '
b1101001 (
b1001110 #
b1001110 &
b1001110 %
#790000
b1001111 "
b1001111 )
b1101000 !
b1101000 '
b1101000 (
b1001111 #
b1001111 &
b1001111 %
#800000
b1010000 "
b1010000 )
b1111000 !
b1111000 '
b1111000 (
b1010000 #
b1010000 &
b1010000 %
#810000
b1010001 "
b1010001 )
b1111001 !
b1111001 '
b1111001 (
b1010001 #
b1010001 &
b1010001 %
#820000
b1010010 "
b1010010 )
b1111011 !
b1111011 '
b1111011 (
b1010010 #
b1010010 &
b1010010 %
#830000
b1010011 "
b1010011 )
b1111010 !
b1111010 '
b1111010 (
b1010011 #
b1010011 &
b1010011 %
#840000
b1010100 "
b1010100 )
b1111110 !
b1111110 '
b1111110 (
b1010100 #
b1010100 &
b1010100 %
#850000
b1010101 "
b1010101 )
b1111111 !
b1111111 '
b1111111 (
b1010101 #
b1010101 &
b1010101 %
#860000
b1010110 "
b1010110 )
b1111101 !
b1111101 '
b1111101 (
b1010110 #
b1010110 &
b1010110 %
#870000
b1010111 "
b1010111 )
b1111100 !
b1111100 '
b1111100 (
b1010111 #
b1010111 &
b1010111 %
#880000
b1011000 "
b1011000 )
b1110100 !
b1110100 '
b1110100 (
b1011000 #
b1011000 &
b1011000 %
#890000
b1011001 "
b1011001 )
b1110101 !
b1110101 '
b1110101 (
b1011001 #
b1011001 &
b1011001 %
#900000
b1011010 "
b1011010 )
b1110111 !
b1110111 '
b1110111 (
b1011010 #
b1011010 &
b1011010 %
#910000
b1011011 "
b1011011 )
b1110110 !
b1110110 '
b1110110 (
b1011011 #
b1011011 &
b1011011 %
#920000
b1011100 "
b1011100 )
b1110010 !
b1110010 '
b1110010 (
b1011100 #
b1011100 &
b1011100 %
#930000
b1011101 "
b1011101 )
b1110011 !
b1110011 '
b1110011 (
b1011101 #
b1011101 &
b1011101 %
#940000
b1011110 "
b1011110 )
b1110001 !
b1110001 '
b1110001 (
b1011110 #
b1011110 &
b1011110 %
#950000
b1011111 "
b1011111 )
b1110000 !
b1110000 '
b1110000 (
b1011111 #
b1011111 &
b1011111 %
#960000
b1100000 "
b1100000 )
b1010000 !
b1010000 '
b1010000 (
b1100000 #
b1100000 &
b1100000 %
#970000
b1100001 "
b1100001 )
b1010001 !
b1010001 '
b1010001 (
b1100001 #
b1100001 &
b1100001 %
#980000
b1100010 "
b1100010 )
b1010011 !
b1010011 '
b1010011 (
b1100010 #
b1100010 &
b1100010 %
#990000
b1100011 "
b1100011 )
b1010010 !
b1010010 '
b1010010 (
b1100011 #
b1100011 &
b1100011 %
#1000000
b1100100 %
