02_basic_RTL/04_sequential_logics/resettable_dffs/resettable_dffs.v
// ==================================================
//	[ VLSISYS Lab. ]
//	* Author		: SoJeong Ok (oksj@sookmyung.ac.kr)
//	* Filename		: resettable_dffs.v
//	* Date			: 2024-09-13 19:32:57
//	* Description	: 
// ==================================================

module	dff_sync
(
	output	reg		o_q,
	input			i_d,
	input			i_clk,
	input			i_rstn
);

	always @(posedge i_clk) begin
		if(!i_rstn) begin
			o_q <= 1'b0;
		end else begin
			o_q <= i_d;
		end
	end

endmodule

module	dff_async
(
	output	reg		o_q,
	input			i_d,
	input			i_clk,
	input			i_rstn
);

	always @(posedge i_clk or negedge i_rstn) begin
		if(!i_rstn) begin
			o_q <= 1'b0;
		end else begin
			o_q <= i_d;
		end
	end

endmodule

02_basic_RTL/04_sequential_logics/resettable_dffs/resettable_dffs_tb.v
// ==================================================
//	[ VLSISYS Lab. ]
//	* Author		: SoJeong Ok (oksj@sookmyung.ac.kr)
//	* Filename		: resettable_dffs_tb.v
//	* Date			: 2024-09-13 19:38:22
//	* Description	: 
// ==================================================
// --------------------------------------------------
//	Define Global Variables
// --------------------------------------------------
`define	CLKFREQ		100		// Clock Freq. (Unit: MHz)
`define	SIMCYCLE	40		// Sim. Cycles

// --------------------------------------------------
//	Includes
// --------------------------------------------------
`include	"resettable_dffs.v"

module resettable_dffs_tb;
// --------------------------------------------------
//	DUT Signals & Instantiate
// --------------------------------------------------
	wire			o_q_sync;
	wire			o_q_async;
	reg				i_d;
	reg				i_clk;
	reg				i_rstn;

	dff_sync
	u_dff_sync(
		.o_q				(o_q_sync			),
		.i_d				(i_d				),
		.i_clk				(i_clk				),
		.i_rstn				(i_rstn				)
	);


	dff_async
	u_dff_async(
		.o_q				(o_q_async			),
		.i_d				(i_d				),
		.i_clk				(i_clk				),
		.i_rstn				(i_rstn				)
	);


// --------------------------------------------------
//		Clock	
// --------------------------------------------------
	always	#(500/`CLKFREQ) i_clk = ~i_clk;

// --------------------------------------------------
//	Tasks 
// --------------------------------------------------
	task init;
		begin
			i_d		= 0;
			i_clk	= 0;
			i_rstn  = 0;
		end
	endtask

	task resetReleaseAfterNCycles;
		input	[9:0]	n;
		begin
			#(n*1000/`CLKFREQ);
			i_rstn = 1'b1;
		end
	endtask
// --------------------------------------------------
//	Test Stimulus
// --------------------------------------------------
	integer		i, j;
	initial begin
		init();
		resetNCycle(4);

		for (i=0; i<`SIMCYCLE; i++) begin
			vecInsert(i);
			vecVerify(i);
		end
		#(1000/`CLKFREQ);
		$finish;
	end

// --------------------------------------------------
//	Dump VCD
// --------------------------------------------------
	reg	[8*32-1:0]	vcd_file;
	initial begin
		if ($value$plusargs("vcd_file=%s", vcd_file)) begin
			$dumpfile(vcd_file);
			$dumpvars;
		end else begin
			$dumpfile("resettable_dffs_tb.vcd");
			$dumpvars;
		end
	end

endmodule

02_basic_RTL/04_sequential_logics/resettable_dffs/vcd/resettable_dffs.vcd
$date
	Thu Sep 19 13:33:28 2024
$end
$version
	Icarus Verilog
$end
$timescale
	1ps
$end
$scope module resettable_dffs_tb $end
$var wire 1 ! o_q_sync $end
$var wire 1 " o_q_async $end
$var reg 1 # i_clk $end
$var reg 1 $ i_d $end
$var reg 1 % i_rstn $end
$var reg 256 & vcd_file [255:0] $end
$var integer 32 ' i [31:0] $end
$var integer 32 ( j [31:0] $end
$scope module u_dff_async $end
$var wire 1 # i_clk $end
$var wire 1 $ i_d $end
$var wire 1 % i_rstn $end
$var reg 1 " o_q $end
$upscope $end
$scope module u_dff_sync $end
$var wire 1 # i_clk $end
$var wire 1 $ i_d $end
$var wire 1 % i_rstn $end
$var reg 1 ! o_q $end
$upscope $end
$scope task init $end
$upscope $end
$scope task resetReleaseAfterNCycles $end
$var reg 10 ) n [9:0] $end
$upscope $end
$upscope $end
$enddefinitions $end
#0
$dumpvars
b100 )
bx (
bx '
b101110001011110111011001100011011001000010111101110010011001010111001101100101011101000111010001100001011000100110110001100101010111110110010001100110011001100111001100101110011101100110001101100100 &
0%
0$
0#
0"
x!
$end
#5000
0!
1#
#10000
0#
#15000
1#
#20000
0#
#25000
1#
#30000
0#
#35000
1#
#40000
0#
b110 (
b0 '
1%
#45000
1#
#46000
1$
#50000
b10 (
b1 '
0#
#55000
1"
1!
1#
#60000
0#
b10 '
#62000
0$
#65000
0"
0!
1#
#70000
0#
b101 (
b11 '
#75000
1#
#80000
0#
b1010 (
b100 '
#85000
1#
#90000
b100 (
b101 '
0#
#94000
0%
1$
#95000
1#
#100000
0#
b1010 (
b110 '
#105000
1#
#110000
b1000 (
b111 '
0#
#115000
1#
#118000
0$
#120000
b100 (
b1000 '
0#
#124000
1$
#125000
1#
#130000
0#
b1001 '
#134000
1%
#135000
1"
1!
1#
#140000
0#
b10 (
b1010 '
#142000
0"
0%
0$
#145000
0!
1#
#150000
0#
b110 (
b1011 '
#155000
1#
#156000
1%
#160000
b11 (
b1100 '
0#
#163000
1$
#165000
1"
1!
1#
#170000
0#
b1 (
b1101 '
#175000
1#
#180000
0$
0#
b0 (
b1110 '
#185000
0"
0!
1#
#190000
0#
b100 (
b1111 '
#194000
0%
1$
#195000
1#
#200000
0#
b10000 '
#204000
0$
#205000
1#
#210000
0#
b1000 (
b10001 '
#215000
1#
#218000
1$
#220000
b10010 '
0#
#225000
1#
#228000
1%
#230000
b1001 (
b10011 '
0#
#235000
1"
1!
1#
#239000
0"
0%
0$
#240000
b100 (
b10100 '
0#
#244000
1%
#245000
0!
1#
#250000
0#
b10 (
b10101 '
#252000
1$
#255000
1"
1!
1#
#260000
0#
b1 (
b10110 '
#261000
0"
0%
0$
#265000
0!
1#
#270000
0#
b101 (
b10111 '
#275000
1"
1!
1#
1%
1$
#280000
0#
b111 (
b11000 '
#285000
1#
#287000
0$
#290000
b1000 (
b11001 '
0#
#295000
0"
0!
1#
#300000
b11 (
b11010 '
0#
#305000
1#
#310000
0#
b1000 (
b11011 '
#315000
1#
#318000
0%
1$
#320000
b100 (
b11100 '
0#
#325000
1#
#330000
0#
b101 (
b11101 '
#335000
1#
0$
#340000
0#
b10 (
b11110 '
#342000
1$
#345000
1#
#350000
0#
b11111 '
#352000
1%
#355000
1"
1!
1#
#360000
0#
b110 (
b100000 '
#365000
1#
#370000
b10 (
b100001 '
0#
#375000
1#
#380000
0#
b1 (
b100010 '
#381000
0"
0%
0$
#385000
0!
1#
#390000
0#
b10 (
b100011 '
#395000
1#
#400000
0#
b1010 (
b100100 '
#405000
1#
#410000
b11 (
b100101 '
0#
1%
#413000
1$
#415000
1"
1!
1#
#420000
0#
b10 (
b100110 '
#422000
0$
#425000
0"
0!
1#
#430000
0#
b100 (
b100111 '
#434000
0%
#435000
1#
#440000
0#
b101000 '
