02_basic_RTL/04_sequential_logics/blockings/blockings.v
// ==================================================
//	[ VLSISYS Lab. ]
//	* Author		: SoJeong Ok (oksj@sookmyung.ac.kr)
//	* Filename		: blockings.v
//	* Description	: 
// ==================================================
 module block
 (
	output	reg		o_q,
	input			i_d,
	input			i_clk
 );

	reg				n1;
	always	@(posedge i_clk) begin
		n1	= i_d;
		o_q	= n1;
	end	

 endmodule


 module nonblock
 (
	output	reg		o_q,
	input			i_d,
	input			i_clk
 );

	reg				n1;
	always	@(posedge i_clk) begin
		n1	<= i_d;
		o_q	<= n1;
	end	

 endmodule

02_basic_RTL/04_sequential_logics/blockings/blockings_tb.v
// ==================================================
//	[ VLSISYS Lab. ]
//	* Author		: SoJeong Ok (oksj@sookmyung.ac.kr)
//	* Filename		: blockings_tb.v
//	* Description	: 
// ==================================================

// --------------------------------------------------
//	Define Global Variables
// --------------------------------------------------
`define	CLKFREQ		100		// Clock Freq. (Unit: MHz)
`define	SIMCYCLE	10		// Sim. Cycles

// --------------------------------------------------
//	Includes
// --------------------------------------------------
`include	"blockings.v"

module blockings_tb;
// --------------------------------------------------
//	DUT Signals & Instantiate
// --------------------------------------------------
	wire		o_q_block;
	wire		o_q_nonblock;
	reg			i_d;
	reg			i_clk;

	block
	u_block(
		.o_q	(o_q_block		),
		.i_d	(i_d			),
		.i_clk	(i_clk			)
	);

	nonblock
	u_nonblock(
		.o_q	(o_q_nonblock	),
		.i_d	(i_d			),
		.i_clk	(i_clk			)
	);


// --------------------------------------------------
//	Clock
// --------------------------------------------------
	always #(500/`CLKFREQ) i_clk = ~i_clk;


// --------------------------------------------------
//	Task
// --------------------------------------------------
	task init;
		begin
			i_d		= 0;
			i_clk	= 0;
		end
	endtask
// --------------------------------------------------
//	Test Stimulus
// --------------------------------------------------
	integer		i, j;
	initial begin
		init();

		for (i=0; i<`SIMCYCLE; i++) begin
			j 	= $urandom_range(0,10);
			#((	(j*0.1))  * 1000/`CLKFREQ);
			i_d	= $urandom;
			#((1-(j*0.1)) * 1000/`CLKFREQ);
		end
		#(1000/`CLKFREQ);
		$finish;
	end

// --------------------------------------------------
//	Dump VCD
// --------------------------------------------------
	reg	[8*32-1:0]	vcd_file;
	initial begin
		if ($value$plusargs("vcd_file=%s", vcd_file)) begin
			$dumpfile(vcd_file);
			$dumpvars;
		end else begin
			$dumpfile("blockings_tb.vcd");
			$dumpvars;
		end
	end

endmodule

02_basic_RTL/04_sequential_logics/blockings/vcd/blockings.vcd
$date
	Fri Sep 13 15:36:30 2024
$end
$version
	Icarus Verilog
$end
$timescale
	1ps
$end
$scope module blockings_tb $end
$var wire 1 ! o_q_nonblock $end
$var wire 1 " o_q_block $end
$var reg 1 # i_clk $end
$var reg 1 $ i_d $end
$var reg 256 % vcd_file [255:0] $end
$var integer 32 & i [31:0] $end
$var integer 32 ' j [31:0] $end
$scope module u_block $end
$var wire 1 # i_clk $end
$var wire 1 $ i_d $end
$var reg 1 ( n1 $end
$var reg 1 " o_q $end
$upscope $end
$scope module u_nonblock $end
$var wire 1 # i_clk $end
$var wire 1 $ i_d $end
$var reg 1 ) n1 $end
$var reg 1 ! o_q $end
$upscope $end
$scope task init $end
$upscope $end
$upscope $end
$enddefinitions $end
#0
$dumpvars
x)
x(
b110 '
b0 &
b101110001011110111011001100011011001000010111101100010011011000110111101100011011010110110100101101110011001110111001100101110011101100110001101100100 %
0$
0#
x"
x!
$end
#5000
0)
0"
0(
1#
#6000
1$
#10000
b0 '
b1 &
0#
#15000
0!
1)
1"
1(
1#
#20000
0#
b101 '
b10 &
#25000
1!
1#
#30000
0#
b10 '
b11 &
#32000
0$
#35000
0)
0"
0(
1#
#40000
0#
b101 '
b100 &
#45000
0!
1)
1"
1(
1#
1$
#50000
0#
b1000 '
b101 &
#55000
1!
1#
#60000
b1010 '
b110 &
0#
#65000
1#
#70000
b111 &
0#
0$
#75000
0)
0"
0(
1#
#80000
b100 '
b1000 &
0#
#85000
0!
1#
#90000
0#
b1010 '
b1001 &
#95000
1#
#100000
b1010 &
0#
1$
#105000
1)
1"
1(
1#
