02_basic_RTL/09_regfile/regfile.v
// ==================================================
//	[ VLSISYS Lab. ]
//	* Author		: SoJeong Ok (oksj@sookmyung.ac.kr)
//	* Filename		: regfile.v
//	* Date			: 2024-09-23 12:58:02
//	* Description	: 
// ==================================================
module regfile
#(	
	parameter	MIF_FILE		= "regfile.mif",
	parameter	BW_DATA			= 32,
	parameter	BW_ADDR			= 5
)
(	
	output 		[BW_DATA-1:0]	o_rd_data0,
	output 		[BW_DATA-1:0]	o_rd_data1,
	input		[BW_ADDR-1:0]	i_rd_addr0,
	input		[BW_ADDR-1:0]	i_rd_addr1,
	input		[BW_DATA-1:0]	i_wr_data,
	input		[BW_ADDR-1:0]	i_wr_addr,
	input						i_wr_en,
	input						i_clk
);

	reg			[BW_DATA-1:0]	rf_arr[0:2**BW_ADDR-1];
	`ifdef	MEM_INIT
		initial begin
			$readmemb(MIF_FILE, rf_arr);
		end
	`endif

	assign	o_rd_data0	= rf_arr[i_rd_addr0];
	assign	o_rd_data1 	= rf_arr[i_rd_addr1];

	always @(posedge i_clk) begin
		if (i_wr_en) begin
			rf_arr[i_wr_addr]	<= i_wr_data;
		end else begin
			rf_arr[i_wr_addr]	<= rf_arr[i_wr_data];
		end
	end

endmodule

02_basic_RTL/09_regfile/regfile_tb.v
// ==================================================
//	[ VLSISYS Lab. ]
//	* Author		: SoJeong Ok (oksj@sookmyung.ac.kr)
//	* Filename		: regfile_tb.v
//	* Date			: 2024-09-23 13:06:54
//	* Description	: 
// ==================================================

// --------------------------------------------------
//	Define Global Variables
// --------------------------------------------------
`define	CLKFREQ		100		// Clock Freq. (Unit: MHz)
`define	SIMCYCLE	`NVEC	// Sim. Cycles
`define NVEC		2**5	// # of Test Vector
`define MEM_INIT
// --------------------------------------------------
//	Includes
// --------------------------------------------------
`include	"regfile.v"

module regfile_tb;
// --------------------------------------------------
//	DUT Signals & Instantiate
// --------------------------------------------------
	parameter	BW_DATA = 32;
	parameter	BW_ADDR = 5;

	wire 		[BW_DATA-1:0]	o_rd_data0;
	wire 		[BW_DATA-1:0]	o_rd_data1;

	reg			[BW_ADDR-1:0]	i_rd_addr0;
	reg			[BW_ADDR-1:0]	i_rd_addr1;
	reg			[BW_DATA-1:0]	i_wr_data;
	reg			[BW_ADDR-1:0]	i_wr_addr;
	reg							i_wr_en;
	reg							i_clk;

	regfile
	#(
		.MIF_FILE			("regfile.mif"		),
		.BW_DATA			(BW_DATA			),
		.BW_ADDR			(BW_ADDR			)
	)
	u_regfile(
		.o_rd_data0			(o_rd_data0			),
		.o_rd_data1			(o_rd_data1			),
		.i_rd_addr0			(i_rd_addr0			),
		.i_rd_addr1			(i_rd_addr1			),
		.i_wr_data			(i_wr_data			),
		.i_wr_addr			(i_wr_addr			),
		.i_wr_en			(i_wr_en			),
		.i_clk				(i_clk				)
	);


// --------------------------------------------------
//	Clock	
// --------------------------------------------------
	always	#(500/`CLKFREQ)	i_clk	= ~i_clk;

// --------------------------------------------------
// 	Tasks	
// --------------------------------------------------
	reg				[8*32-1:0]		taskState;
	task init;
		begin
					i_rd_addr0	= 0;
					i_rd_addr1	= 0;
					i_wr_data	= 0;
					i_wr_addr	= 0;
					i_wr_en		= 0;
					i_clk		= 0;
		end
	endtask

	task rfWR;
		input		[BW_DATA-1:0]	ti_wr_data;
		input		[BW_ADDR-1:0]	ti_wr_addr;
		begin
				@ (negedge i_clk) begin
					taskState	=	"WR";
					i_wr_data	= ti_wr_data;
					i_wr_addr	= ti_wr_addr;
					i_wr_en		= 1;		
				end
		end
	endtask


	task rfRD;
		input		[BW_ADDR-1:0]	ti_rd_addr0;
		input		[BW_ADDR-1:0]	ti_rd_addr1;
		begin
				@ (negedge i_clk) begin
					taskState	=	"RD";
					i_rd_addr0	= ti_rd_addr0;
					i_rd_addr1	= ti_rd_addr1;
					i_wr_en		= 0;
				
				end
		end
	endtask



// --------------------------------------------------
//	Test Stimulus
// --------------------------------------------------
	integer		i, j;
	initial begin
		init();
		#(4*1000/`CLKFREQ);
		for (i=0; i<`SIMCYCLE; i++) begin
			rfWR(i, i);
		end
		
		for (i=0; i<`SIMCYCLE; i++) begin
			rfRD(i, i);
		end
		
		for (i=0; i<`SIMCYCLE; i++) begin
			rfWR(i, i);
			#(1000/`CLKFREQ);
			rfRD(i, i);
		end
		#(1000/`CLKFREQ);
		$finish;
	end

// --------------------------------------------------
//	Dump VCD
// --------------------------------------------------
	reg	[8*32-1:0]	vcd_file;
	initial begin
		if ($value$plusargs("vcd_file=%s", vcd_file)) begin
			$dumpfile(vcd_file);
			$dumpvars;
			for	(i=0; i<`SIMCYCLE; i++) begin
				$dumpvars(0, u_regfile.rf_arr[i]);
			end
		end else begin
			$dumpfile("regfile_tb.vcd");
			$dumpvars;
		end
	end

endmodule

02_basic_RTL/09_regfile/vcd/regfile.vcd
$date
	Mon Sep 23 13:23:01 2024
$end
$version
	Icarus Verilog
$end
$timescale
	1ps
$end
$scope module regfile_tb $end
$var wire 32 ! o_rd_data1 [31:0] $end
$var wire 32 " o_rd_data0 [31:0] $end
$var reg 1 # i_clk $end
$var reg 5 $ i_rd_addr0 [4:0] $end
$var reg 5 % i_rd_addr1 [4:0] $end
$var reg 5 & i_wr_addr [4:0] $end
$var reg 32 ' i_wr_data [31:0] $end
$var reg 1 ( i_wr_en $end
$var reg 256 ) taskState [255:0] $end
$var reg 256 * vcd_file [255:0] $end
$var integer 32 + i [31:0] $end
$scope module u_regfile $end
$var wire 1 # i_clk $end
$var wire 5 , i_rd_addr0 [4:0] $end
$var wire 5 - i_rd_addr1 [4:0] $end
$var wire 5 . i_wr_addr [4:0] $end
$var wire 32 / i_wr_data [31:0] $end
$var wire 1 ( i_wr_en $end
$var wire 32 0 o_rd_data0 [31:0] $end
$var wire 32 1 o_rd_data1 [31:0] $end
$upscope $end
$scope task init $end
$upscope $end
$scope task rfRD $end
$var reg 5 2 ti_rd_addr0 [4:0] $end
$var reg 5 3 ti_rd_addr1 [4:0] $end
$upscope $end
$scope task rfWR $end
$var reg 5 4 ti_wr_addr [4:0] $end
$var reg 32 5 ti_wr_data [31:0] $end
$upscope $end
$upscope $end
$scope module regfile_tb $end
$scope module u_regfile $end
$var reg 32 6 \rf_arr[0] [31:0] $end
$upscope $end
$upscope $end
$scope module regfile_tb $end
$scope module u_regfile $end
$var reg 32 7 \rf_arr[1] [31:0] $end
$upscope $end
$upscope $end
$scope module regfile_tb $end
$scope module u_regfile $end
$var reg 32 8 \rf_arr[2] [31:0] $end
$upscope $end
$upscope $end
$scope module regfile_tb $end
$scope module u_regfile $end
$var reg 32 9 \rf_arr[3] [31:0] $end
$upscope $end
$upscope $end
$scope module regfile_tb $end
$scope module u_regfile $end
$var reg 32 : \rf_arr[4] [31:0] $end
$upscope $end
$upscope $end
$scope module regfile_tb $end
$scope module u_regfile $end
$var reg 32 ; \rf_arr[5] [31:0] $end
$upscope $end
$upscope $end
$scope module regfile_tb $end
$scope module u_regfile $end
$var reg 32 < \rf_arr[6] [31:0] $end
$upscope $end
$upscope $end
$scope module regfile_tb $end
$scope module u_regfile $end
$var reg 32 = \rf_arr[7] [31:0] $end
$upscope $end
$upscope $end
$scope module regfile_tb $end
$scope module u_regfile $end
$var reg 32 > \rf_arr[8] [31:0] $end
$upscope $end
$upscope $end
$scope module regfile_tb $end
$scope module u_regfile $end
$var reg 32 ? \rf_arr[9] [31:0] $end
$upscope $end
$upscope $end
$scope module regfile_tb $end
$scope module u_regfile $end
$var reg 32 @ \rf_arr[10] [31:0] $end
$upscope $end
$upscope $end
$scope module regfile_tb $end
$scope module u_regfile $end
$var reg 32 A \rf_arr[11] [31:0] $end
$upscope $end
$upscope $end
$scope module regfile_tb $end
$scope module u_regfile $end
$var reg 32 B \rf_arr[12] [31:0] $end
$upscope $end
$upscope $end
$scope module regfile_tb $end
$scope module u_regfile $end
$var reg 32 C \rf_arr[13] [31:0] $end
$upscope $end
$upscope $end
$scope module regfile_tb $end
$scope module u_regfile $end
$var reg 32 D \rf_arr[14] [31:0] $end
$upscope $end
$upscope $end
$scope module regfile_tb $end
$scope module u_regfile $end
$var reg 32 E \rf_arr[15] [31:0] $end
$upscope $end
$upscope $end
$scope module regfile_tb $end
$scope module u_regfile $end
$var reg 32 F \rf_arr[16] [31:0] $end
$upscope $end
$upscope $end
$scope module regfile_tb $end
$scope module u_regfile $end
$var reg 32 G \rf_arr[17] [31:0] $end
$upscope $end
$upscope $end
$scope module regfile_tb $end
$scope module u_regfile $end
$var reg 32 H \rf_arr[18] [31:0] $end
$upscope $end
$upscope $end
$scope module regfile_tb $end
$scope module u_regfile $end
$var reg 32 I \rf_arr[19] [31:0] $end
$upscope $end
$upscope $end
$scope module regfile_tb $end
$scope module u_regfile $end
$var reg 32 J \rf_arr[20] [31:0] $end
$upscope $end
$upscope $end
$scope module regfile_tb $end
$scope module u_regfile $end
$var reg 32 K \rf_arr[21] [31:0] $end
$upscope $end
$upscope $end
$scope module regfile_tb $end
$scope module u_regfile $end
$var reg 32 L \rf_arr[22] [31:0] $end
$upscope $end
$upscope $end
$scope module regfile_tb $end
$scope module u_regfile $end
$var reg 32 M \rf_arr[23] [31:0] $end
$upscope $end
$upscope $end
$scope module regfile_tb $end
$scope module u_regfile $end
$var reg 32 N \rf_arr[24] [31:0] $end
$upscope $end
$upscope $end
$scope module regfile_tb $end
$scope module u_regfile $end
$var reg 32 O \rf_arr[25] [31:0] $end
$upscope $end
$upscope $end
$scope module regfile_tb $end
$scope module u_regfile $end
$var reg 32 P \rf_arr[26] [31:0] $end
$upscope $end
$upscope $end
$scope module regfile_tb $end
$scope module u_regfile $end
$var reg 32 Q \rf_arr[27] [31:0] $end
$upscope $end
$upscope $end
$scope module regfile_tb $end
$scope module u_regfile $end
$var reg 32 R \rf_arr[28] [31:0] $end
$upscope $end
$upscope $end
$scope module regfile_tb $end
$scope module u_regfile $end
$var reg 32 S \rf_arr[29] [31:0] $end
$upscope $end
$upscope $end
$scope module regfile_tb $end
$scope module u_regfile $end
$var reg 32 T \rf_arr[30] [31:0] $end
$upscope $end
$upscope $end
$scope module regfile_tb $end
$scope module u_regfile $end
$var reg 32 U \rf_arr[31] [31:0] $end
$upscope $end
$upscope $end
$enddefinitions $end
#0
$dumpvars
b0 U
b0 T
b0 S
b0 R
b0 Q
b0 P
b0 O
b0 N
b0 M
b0 L
b0 K
b0 J
b0 I
b0 H
b0 G
b0 F
b0 E
b0 D
b0 C
b0 B
b100000000000 A
b10000000000 @
b1000000000 ?
b100000000 >
b10000000 =
b1000000 <
b100000 ;
b10000 :
b1000 9
b100 8
b10 7
b1 6
bx 5
bx 4
bx 3
bx 2
b1 1
b1 0
b0 /
b0 .
b0 -
b0 ,
b100000 +
b10111000101111011101100110001101100100001011110111001001100101011001110110011001101001011011000110010100101110011101100110001101100100 *
bx )
0(
b0 '
b0 &
b0 %
b0 $
0#
b1 "
b1 !
$end
#5000
b1 6
1#
#10000
0#
#15000
b1 6
1#
#20000
0#
#25000
b1 6
1#
#30000
0#
#35000
b1 6
1#
#40000
1(
b101011101010010 )
0#
b1 4
b1 5
b1 +
#45000
b0 6
b0 "
b0 0
b0 !
b0 1
1#
#50000
b10 4
b10 5
b10 +
b1 &
b1 .
b1 '
b1 /
0#
#55000
b1 7
1#
#60000
b11 4
b11 5
b11 +
b10 &
b10 .
b10 '
b10 /
0#
#65000
b10 8
1#
#70000
b100 4
b100 5
b100 +
b11 &
b11 .
b11 '
b11 /
0#
#75000
b11 9
1#
#80000
b101 4
b101 5
b101 +
b100 &
b100 .
b100 '
b100 /
0#
#85000
b100 :
1#
#90000
b110 4
b110 5
b110 +
b101 &
b101 .
b101 '
b101 /
0#
#95000
b101 ;
1#
#100000
b111 4
b111 5
b111 +
b110 &
b110 .
b110 '
b110 /
0#
#105000
b110 <
1#
#110000
b1000 4
b1000 5
b1000 +
b111 &
b111 .
b111 '
b111 /
0#
#115000
b111 =
1#
#120000
b1001 4
b1001 5
b1001 +
b1000 &
b1000 .
b1000 '
b1000 /
0#
#125000
b1000 >
1#
#130000
b1010 4
b1010 5
b1010 +
b1001 &
b1001 .
b1001 '
b1001 /
0#
#135000
b1001 ?
1#
#140000
b1011 4
b1011 5
b1011 +
b1010 &
b1010 .
b1010 '
b1010 /
0#
#145000
b1010 @
1#
#150000
b1100 4
b1100 5
b1100 +
b1011 &
b1011 .
b1011 '
b1011 /
0#
#155000
b1011 A
1#
#160000
b1101 4
b1101 5
b1101 +
b1100 &
b1100 .
b1100 '
b1100 /
0#
#165000
b1100 B
1#
#170000
b1110 4
b1110 5
b1110 +
b1101 &
b1101 .
b1101 '
b1101 /
0#
#175000
b1101 C
1#
#180000
b1111 4
b1111 5
b1111 +
b1110 &
b1110 .
b1110 '
b1110 /
0#
#185000
b1110 D
1#
#190000
b10000 4
b10000 5
b10000 +
b1111 &
b1111 .
b1111 '
b1111 /
0#
#195000
b1111 E
1#
#200000
b10001 4
b10001 5
b10001 +
b10000 &
b10000 .
b10000 '
b10000 /
0#
#205000
b10000 F
1#
#210000
b10010 4
b10010 5
b10010 +
b10001 &
b10001 .
b10001 '
b10001 /
0#
#215000
b10001 G
1#
#220000
b10011 4
b10011 5
b10011 +
b10010 &
b10010 .
b10010 '
b10010 /
0#
#225000
b10010 H
1#
#230000
b10100 4
b10100 5
b10100 +
b10011 &
b10011 .
b10011 '
b10011 /
0#
#235000
b10011 I
1#
#240000
b10101 4
b10101 5
b10101 +
b10100 &
b10100 .
b10100 '
b10100 /
0#
#245000
b10100 J
1#
#250000
b10110 4
b10110 5
b10110 +
b10101 &
b10101 .
b10101 '
b10101 /
0#
#255000
b10101 K
1#
#260000
b10111 4
b10111 5
b10111 +
b10110 &
b10110 .
b10110 '
b10110 /
0#
#265000
b10110 L
1#
#270000
b11000 4
b11000 5
b11000 +
b10111 &
b10111 .
b10111 '
b10111 /
0#
#275000
b10111 M
1#
#280000
b11001 4
b11001 5
b11001 +
b11000 &
b11000 .
b11000 '
b11000 /
0#
#285000
b11000 N
1#
#290000
b11010 4
b11010 5
b11010 +
b11001 &
b11001 .
b11001 '
b11001 /
0#
#295000
b11001 O
1#
#300000
b11011 4
b11011 5
b11011 +
b11010 &
b11010 .
b11010 '
b11010 /
0#
#305000
b11010 P
1#
#310000
b11100 4
b11100 5
b11100 +
b11011 &
b11011 .
b11011 '
b11011 /
0#
#315000
b11011 Q
1#
#320000
b11101 4
b11101 5
b11101 +
b11100 &
b11100 .
b11100 '
b11100 /
0#
#325000
b11100 R
1#
#330000
b11110 4
b11110 5
b11110 +
b11101 &
b11101 .
b11101 '
b11101 /
0#
#335000
b11101 S
1#
#340000
b11111 4
b11111 5
b11111 +
b11110 &
b11110 .
b11110 '
b11110 /
0#
#345000
b11110 T
1#
#350000
b0 3
b0 2
b0 +
b11111 &
b11111 .
b11111 '
b11111 /
0#
#355000
b11111 U
1#
#360000
b1 3
b1 2
b1 +
0(
b101001001000100 )
0#
#365000
b11111 U
1#
#370000
b10 3
b10 2
b10 +
b1 !
b1 1
b1 %
b1 -
b1 "
b1 0
b1 $
b1 ,
0#
#375000
b11111 U
1#
#380000
b11 3
b11 2
b11 +
b10 !
b10 1
b10 %
b10 -
b10 "
b10 0
b10 $
b10 ,
0#
#385000
b11111 U
1#
#390000
b100 3
b100 2
b100 +
b11 !
b11 1
b11 %
b11 -
b11 "
b11 0
b11 $
b11 ,
0#
#395000
b11111 U
1#
#400000
b101 3
b101 2
b101 +
b100 !
b100 1
b100 %
b100 -
b100 "
b100 0
b100 $
b100 ,
0#
#405000
b11111 U
1#
#410000
b110 3
b110 2
b110 +
b101 !
b101 1
b101 %
b101 -
b101 "
b101 0
b101 $
b101 ,
0#
#415000
b11111 U
1#
#420000
b111 3
b111 2
b111 +
b110 !
b110 1
b110 %
b110 -
b110 "
b110 0
b110 $
b110 ,
0#
#425000
b11111 U
1#
#430000
b1000 3
b1000 2
b1000 +
b111 !
b111 1
b111 %
b111 -
b111 "
b111 0
b111 $
b111 ,
0#
#435000
b11111 U
1#
#440000
b1001 3
b1001 2
b1001 +
b1000 !
b1000 1
b1000 %
b1000 -
b1000 "
b1000 0
b1000 $
b1000 ,
0#
#445000
b11111 U
1#
#450000
b1010 3
b1010 2
b1010 +
b1001 !
b1001 1
b1001 %
b1001 -
b1001 "
b1001 0
b1001 $
b1001 ,
0#
#455000
b11111 U
1#
#460000
b1011 3
b1011 2
b1011 +
b1010 !
b1010 1
b1010 %
b1010 -
b1010 "
b1010 0
b1010 $
b1010 ,
0#
#465000
b11111 U
1#
#470000
b1100 3
b1100 2
b1100 +
b1011 !
b1011 1
b1011 %
b1011 -
b1011 "
b1011 0
b1011 $
b1011 ,
0#
#475000
b11111 U
1#
#480000
b1101 3
b1101 2
b1101 +
b1100 !
b1100 1
b1100 %
b1100 -
b1100 "
b1100 0
b1100 $
b1100 ,
0#
#485000
b11111 U
1#
#490000
b1110 3
b1110 2
b1110 +
b1101 !
b1101 1
b1101 %
b1101 -
b1101 "
b1101 0
b1101 $
b1101 ,
0#
#495000
b11111 U
1#
#500000
b1111 3
b1111 2
b1111 +
b1110 !
b1110 1
b1110 %
b1110 -
b1110 "
b1110 0
b1110 $
b1110 ,
0#
#505000
b11111 U
1#
#510000
b10000 3
b10000 2
b10000 +
b1111 !
b1111 1
b1111 %
b1111 -
b1111 "
b1111 0
b1111 $
b1111 ,
0#
#515000
b11111 U
1#
#520000
b10001 3
b10001 2
b10001 +
b10000 !
b10000 1
b10000 %
b10000 -
b10000 "
b10000 0
b10000 $
b10000 ,
0#
#525000
b11111 U
1#
#530000
b10010 3
b10010 2
b10010 +
b10001 !
b10001 1
b10001 %
b10001 -
b10001 "
b10001 0
b10001 $
b10001 ,
0#
#535000
b11111 U
1#
#540000
b10011 3
b10011 2
b10011 +
b10010 !
b10010 1
b10010 %
b10010 -
b10010 "
b10010 0
b10010 $
b10010 ,
0#
#545000
b11111 U
1#
#550000
b10100 3
b10100 2
b10100 +
b10011 !
b10011 1
b10011 %
b10011 -
b10011 "
b10011 0
b10011 $
b10011 ,
0#
#555000
b11111 U
1#
#560000
b10101 3
b10101 2
b10101 +
b10100 !
b10100 1
b10100 %
b10100 -
b10100 "
b10100 0
b10100 $
b10100 ,
0#
#565000
b11111 U
1#
#570000
b10110 3
b10110 2
b10110 +
b10101 !
b10101 1
b10101 %
b10101 -
b10101 "
b10101 0
b10101 $
b10101 ,
0#
#575000
b11111 U
1#
#580000
b10111 3
b10111 2
b10111 +
b10110 !
b10110 1
b10110 %
b10110 -
b10110 "
b10110 0
b10110 $
b10110 ,
0#
#585000
b11111 U
1#
#590000
b11000 3
b11000 2
b11000 +
b10111 !
b10111 1
b10111 %
b10111 -
b10111 "
b10111 0
b10111 $
b10111 ,
0#
#595000
b11111 U
1#
#600000
b11001 3
b11001 2
b11001 +
b11000 !
b11000 1
b11000 %
b11000 -
b11000 "
b11000 0
b11000 $
b11000 ,
0#
#605000
b11111 U
1#
#610000
b11010 3
b11010 2
b11010 +
b11001 !
b11001 1
b11001 %
b11001 -
b11001 "
b11001 0
b11001 $
b11001 ,
0#
#615000
b11111 U
1#
#620000
b11011 3
b11011 2
b11011 +
b11010 !
b11010 1
b11010 %
b11010 -
b11010 "
b11010 0
b11010 $
b11010 ,
0#
#625000
b11111 U
1#
#630000
b11100 3
b11100 2
b11100 +
b11011 !
b11011 1
b11011 %
b11011 -
b11011 "
b11011 0
b11011 $
b11011 ,
0#
#635000
b11111 U
1#
#640000
b11101 3
b11101 2
b11101 +
b11100 !
b11100 1
b11100 %
b11100 -
b11100 "
b11100 0
b11100 $
b11100 ,
0#
#645000
b11111 U
1#
#650000
b11110 3
b11110 2
b11110 +
b11101 !
b11101 1
b11101 %
b11101 -
b11101 "
b11101 0
b11101 $
b11101 ,
0#
#655000
b11111 U
1#
#660000
b11111 3
b11111 2
b11111 +
b11110 !
b11110 1
b11110 %
b11110 -
b11110 "
b11110 0
b11110 $
b11110 ,
0#
#665000
b11111 U
1#
#670000
b0 4
b0 5
b0 +
b11111 !
b11111 1
b11111 %
b11111 -
b11111 "
b11111 0
b11111 $
b11111 ,
0#
#675000
b11111 U
1#
#680000
1(
b0 &
b0 .
b0 '
b0 /
b101011101010010 )
0#
#685000
b0 6
1#
#690000
b1 4
b1 5
b1 +
0(
b0 !
b0 1
b0 %
b0 -
b0 "
b0 0
b0 $
b0 ,
b101001001000100 )
0#
b0 3
b0 2
#695000
b0 6
1#
#700000
1(
b1 &
b1 .
b1 '
b1 /
b101011101010010 )
0#
#705000
b1 7
1#
#710000
b10 4
b10 5
b10 +
0(
b1 !
b1 1
b1 %
b1 -
b1 "
b1 0
b1 $
b1 ,
b101001001000100 )
0#
b1 3
b1 2
#715000
b1 7
1#
#720000
1(
b10 &
b10 .
b10 '
b10 /
b101011101010010 )
0#
#725000
b10 8
1#
#730000
b11 4
b11 5
b11 +
0(
b10 !
b10 1
b10 %
b10 -
b10 "
b10 0
b10 $
b10 ,
b101001001000100 )
0#
b10 3
b10 2
#735000
b10 8
1#
#740000
1(
b11 &
b11 .
b11 '
b11 /
b101011101010010 )
0#
#745000
b11 9
1#
#750000
b100 4
b100 5
b100 +
0(
b11 !
b11 1
b11 %
b11 -
b11 "
b11 0
b11 $
b11 ,
b101001001000100 )
0#
b11 3
b11 2
#755000
b11 9
1#
#760000
1(
b100 &
b100 .
b100 '
b100 /
b101011101010010 )
0#
#765000
b100 :
1#
#770000
b101 4
b101 5
b101 +
0(
b100 !
b100 1
b100 %
b100 -
b100 "
b100 0
b100 $
b100 ,
b101001001000100 )
0#
b100 3
b100 2
#775000
b100 :
1#
#780000
1(
b101 &
b101 .
b101 '
b101 /
b101011101010010 )
0#
#785000
b101 ;
1#
#790000
b110 4
b110 5
b110 +
0(
b101 !
b101 1
b101 %
b101 -
b101 "
b101 0
b101 $
b101 ,
b101001001000100 )
0#
b101 3
b101 2
#795000
b101 ;
1#
#800000
1(
b110 &
b110 .
b110 '
b110 /
b101011101010010 )
0#
#805000
b110 <
1#
#810000
b111 4
b111 5
b111 +
0(
b110 !
b110 1
b110 %
b110 -
b110 "
b110 0
b110 $
b110 ,
b101001001000100 )
0#
b110 3
b110 2
#815000
b110 <
1#
#820000
1(
b111 &
b111 .
b111 '
b111 /
b101011101010010 )
0#
#825000
b111 =
1#
#830000
b1000 4
b1000 5
b1000 +
0(
b111 !
b111 1
b111 %
b111 -
b111 "
b111 0
b111 $
b111 ,
b101001001000100 )
0#
b111 3
b111 2
#835000
b111 =
1#
#840000
1(
b1000 &
b1000 .
b1000 '
b1000 /
b101011101010010 )
0#
#845000
b1000 >
1#
#850000
b1001 4
b1001 5
b1001 +
0(
b1000 !
b1000 1
b1000 %
b1000 -
b1000 "
b1000 0
b1000 $
b1000 ,
b101001001000100 )
0#
b1000 3
b1000 2
#855000
b1000 >
1#
#860000
1(
b1001 &
b1001 .
b1001 '
b1001 /
b101011101010010 )
0#
#865000
b1001 ?
1#
#870000
b1010 4
b1010 5
b1010 +
0(
b1001 !
b1001 1
b1001 %
b1001 -
b1001 "
b1001 0
b1001 $
b1001 ,
b101001001000100 )
0#
b1001 3
b1001 2
#875000
b1001 ?
1#
#880000
1(
b1010 &
b1010 .
b1010 '
b1010 /
b101011101010010 )
0#
#885000
b1010 @
1#
#890000
b1011 4
b1011 5
b1011 +
0(
b1010 !
b1010 1
b1010 %
b1010 -
b1010 "
b1010 0
b1010 $
b1010 ,
b101001001000100 )
0#
b1010 3
b1010 2
#895000
b1010 @
1#
#900000
1(
b1011 &
b1011 .
b1011 '
b1011 /
b101011101010010 )
0#
#905000
b1011 A
1#
#910000
b1100 4
b1100 5
b1100 +
0(
b1011 !
b1011 1
b1011 %
b1011 -
b1011 "
b1011 0
b1011 $
b1011 ,
b101001001000100 )
0#
b1011 3
b1011 2
#915000
b1011 A
1#
#920000
1(
b1100 &
b1100 .
b1100 '
b1100 /
b101011101010010 )
0#
#925000
b1100 B
1#
#930000
b1101 4
b1101 5
b1101 +
0(
b1100 !
b1100 1
b1100 %
b1100 -
b1100 "
b1100 0
b1100 $
b1100 ,
b101001001000100 )
0#
b1100 3
b1100 2
#935000
b1100 B
1#
#940000
1(
b1101 &
b1101 .
b1101 '
b1101 /
b101011101010010 )
0#
#945000
b1101 C
1#
#950000
b1110 4
b1110 5
b1110 +
0(
b1101 !
b1101 1
b1101 %
b1101 -
b1101 "
b1101 0
b1101 $
b1101 ,
b101001001000100 )
0#
b1101 3
b1101 2
#955000
b1101 C
1#
#960000
1(
b1110 &
b1110 .
b1110 '
b1110 /
b101011101010010 )
0#
#965000
b1110 D
1#
#970000
b1111 4
b1111 5
b1111 +
0(
b1110 !
b1110 1
b1110 %
b1110 -
b1110 "
b1110 0
b1110 $
b1110 ,
b101001001000100 )
0#
b1110 3
b1110 2
#975000
b1110 D
1#
#980000
1(
b1111 &
b1111 .
b1111 '
b1111 /
b101011101010010 )
0#
#985000
b1111 E
1#
#990000
b10000 4
b10000 5
b10000 +
0(
b1111 !
b1111 1
b1111 %
b1111 -
b1111 "
b1111 0
b1111 $
b1111 ,
b101001001000100 )
0#
b1111 3
b1111 2
#995000
b1111 E
1#
#1000000
1(
b10000 &
b10000 .
b10000 '
b10000 /
b101011101010010 )
0#
#1005000
b10000 F
1#
#1010000
b10001 4
b10001 5
b10001 +
0(
b10000 !
b10000 1
b10000 %
b10000 -
b10000 "
b10000 0
b10000 $
b10000 ,
b101001001000100 )
0#
b10000 3
b10000 2
#1015000
b10000 F
1#
#1020000
1(
b10001 &
b10001 .
b10001 '
b10001 /
b101011101010010 )
0#
#1025000
b10001 G
1#
#1030000
b10010 4
b10010 5
b10010 +
0(
b10001 !
b10001 1
b10001 %
b10001 -
b10001 "
b10001 0
b10001 $
b10001 ,
b101001001000100 )
0#
b10001 3
b10001 2
#1035000
b10001 G
1#
#1040000
1(
b10010 &
b10010 .
b10010 '
b10010 /
b101011101010010 )
0#
#1045000
b10010 H
1#
#1050000
b10011 4
b10011 5
b10011 +
0(
b10010 !
b10010 1
b10010 %
b10010 -
b10010 "
b10010 0
b10010 $
b10010 ,
b101001001000100 )
0#
b10010 3
b10010 2
#1055000
b10010 H
1#
#1060000
1(
b10011 &
b10011 .
b10011 '
b10011 /
b101011101010010 )
0#
#1065000
b10011 I
1#
#1070000
b10100 4
b10100 5
b10100 +
0(
b10011 !
b10011 1
b10011 %
b10011 -
b10011 "
b10011 0
b10011 $
b10011 ,
b101001001000100 )
0#
b10011 3
b10011 2
#1075000
b10011 I
1#
#1080000
1(
b10100 &
b10100 .
b10100 '
b10100 /
b101011101010010 )
0#
#1085000
b10100 J
1#
#1090000
b10101 4
b10101 5
b10101 +
0(
b10100 !
b10100 1
b10100 %
b10100 -
b10100 "
b10100 0
b10100 $
b10100 ,
b101001001000100 )
0#
b10100 3
b10100 2
#1095000
b10100 J
1#
#1100000
1(
b10101 &
b10101 .
b10101 '
b10101 /
b101011101010010 )
0#
#1105000
b10101 K
1#
#1110000
b10110 4
b10110 5
b10110 +
0(
b10101 !
b10101 1
b10101 %
b10101 -
b10101 "
b10101 0
b10101 $
b10101 ,
b101001001000100 )
0#
b10101 3
b10101 2
#1115000
b10101 K
1#
#1120000
1(
b10110 &
b10110 .
b10110 '
b10110 /
b101011101010010 )
0#
#1125000
b10110 L
1#
#1130000
b10111 4
b10111 5
b10111 +
0(
b10110 !
b10110 1
b10110 %
b10110 -
b10110 "
b10110 0
b10110 $
b10110 ,
b101001001000100 )
0#
b10110 3
b10110 2
#1135000
b10110 L
1#
#1140000
1(
b10111 &
b10111 .
b10111 '
b10111 /
b101011101010010 )
0#
#1145000
b10111 M
1#
#1150000
b11000 4
b11000 5
b11000 +
0(
b10111 !
b10111 1
b10111 %
b10111 -
b10111 "
b10111 0
b10111 $
b10111 ,
b101001001000100 )
0#
b10111 3
b10111 2
#1155000
b10111 M
1#
#1160000
1(
b11000 &
b11000 .
b11000 '
b11000 /
b101011101010010 )
0#
#1165000
b11000 N
1#
#1170000
b11001 4
b11001 5
b11001 +
0(
b11000 !
b11000 1
b11000 %
b11000 -
b11000 "
b11000 0
b11000 $
b11000 ,
b101001001000100 )
0#
b11000 3
b11000 2
#1175000
b11000 N
1#
#1180000
1(
b11001 &
b11001 .
b11001 '
b11001 /
b101011101010010 )
0#
#1185000
b11001 O
1#
#1190000
b11010 4
b11010 5
b11010 +
0(
b11001 !
b11001 1
b11001 %
b11001 -
b11001 "
b11001 0
b11001 $
b11001 ,
b101001001000100 )
0#
b11001 3
b11001 2
#1195000
b11001 O
1#
#1200000
1(
b11010 &
b11010 .
b11010 '
b11010 /
b101011101010010 )
0#
#1205000
b11010 P
1#
#1210000
b11011 4
b11011 5
b11011 +
0(
b11010 !
b11010 1
b11010 %
b11010 -
b11010 "
b11010 0
b11010 $
b11010 ,
b101001001000100 )
0#
b11010 3
b11010 2
#1215000
b11010 P
1#
#1220000
1(
b11011 &
b11011 .
b11011 '
b11011 /
b101011101010010 )
0#
#1225000
b11011 Q
1#
#1230000
b11100 4
b11100 5
b11100 +
0(
b11011 !
b11011 1
b11011 %
b11011 -
b11011 "
b11011 0
b11011 $
b11011 ,
b101001001000100 )
0#
b11011 3
b11011 2
#1235000
b11011 Q
1#
#1240000
1(
b11100 &
b11100 .
b11100 '
b11100 /
b101011101010010 )
0#
#1245000
b11100 R
1#
#1250000
b11101 4
b11101 5
b11101 +
0(
b11100 !
b11100 1
b11100 %
b11100 -
b11100 "
b11100 0
b11100 $
b11100 ,
b101001001000100 )
0#
b11100 3
b11100 2
#1255000
b11100 R
1#
#1260000
1(
b11101 &
b11101 .
b11101 '
b11101 /
b101011101010010 )
0#
#1265000
b11101 S
1#
